Metadata-Version: 2.1
Name: distributionsByHam
Version: 0.1
Summary: Gaussian distributions
Author-email: syedhamza097@gmail.com
